rubithon/__init__.py
rubithon/client.py
rubithon/crypto/__init__.py
rubithon/crypto/crypto.py
rubithon/gadgets/__init__.py
rubithon/gadgets/classino.py
rubithon/gadgets/exceptions.py
rubithon/gadgets/methods.py
rubithon/gadgets/thumbnail.py
rubithon/network/__init__.py
rubithon/network/connection.py
rubithon/network/proxies.py
rubithon/sessions/__init__.py
rubithon/sessions/sqliteSession.py
rubithon/sessions/stringSession.py
rubithon/structs/__init__.py
rubithon/structs/handlers.py
rubithon/structs/models.py
rubithon/structs/results.py
rubithon/structs/struct.py
rubithon-1.1.1.dist-info/METADATA
rubithon-1.1.1.dist-info/WHEEL
rubithon-1.1.1.dist-info/top_level.txt
rubithon-1.1.1.dist-info/RECORD
