Metadata-Version: 2.1
Name: rubithon
Version: 1.1.1
Summary: ribithon created by milad heidary
Home-page: https://github.com/irmilad/rubika
Download-URL: https://github.com/irmilad/rubika/releases/latest
Author: milad heidary
License: MIT
Project-URL: Tracker, https://github.com/irmilad/rubika/issues
Project-URL: Source, https://github.com/irmilad/rubika
Project-URL: Documentation, https://github.com/irmilad/rubika/blob/main/README.md
Keywords: milad heidary,messenger,python,python3,api,self,Rubika,rubika,bot,robot,library,rubikalib,rubikalibrary,rubika.ir,web.rubika.ir,m.rubika.ir
Classifier: Development Status :: 5 - Production/Stable
Classifier: Intended Audience :: Developers
Classifier: Natural Language :: English
Classifier: License :: OSI Approved :: GNU Lesser General Public License v3 (LGPLv3)
Classifier: Operating System :: OS Independent
Classifier: Programming Language :: Python
Classifier: Programming Language :: Python :: 3
Classifier: Programming Language :: Python :: 3.5
Classifier: Programming Language :: Python :: 3.6
Classifier: Programming Language :: Python :: 3.7
Classifier: Programming Language :: Python :: 3.8
Classifier: Programming Language :: Python :: 3.9
Classifier: Programming Language :: Python :: 3.10
Classifier: Programming Language :: Python :: 3.11
Classifier: Programming Language :: Python :: Implementation
Classifier: Programming Language :: Python :: Implementation :: CPython
Classifier: Programming Language :: Python :: Implementation :: PyPy
Classifier: Topic :: Internet
Classifier: Topic :: Communications
Classifier: Topic :: Communications :: Chat
Classifier: Topic :: Software Development :: Libraries
Classifier: Topic :: Software Development :: Libraries :: Python Modules
Classifier: Topic :: Software Development :: Libraries :: Application Frameworks
Requires-Python: ~=3.5
Requires-Dist: requests
Requires-Dist: pycryptodome (==3.10.1)
Requires-Dist: urllib3
Requires-Dist: tqdm
Requires-Dist: rich
Requires-Dist: websocket-client
